README.rst
setup.cfg
setup.py
attackapi/__init__.py
attackapi/cli.py
attackapi/core.py
attackapi/foo_flymake.py
attackapi/store_requests.py
attackapi/utils.py
attackapi.egg-info/PKG-INFO
attackapi.egg-info/SOURCES.txt
attackapi.egg-info/dependency_links.txt
attackapi.egg-info/entry_points.txt
attackapi.egg-info/not-zip-safe
attackapi.egg-info/requires.txt
attackapi.egg-info/top_level.txt