Metadata-Version: 1.1
Name: attackapi
Version: 0.1.1
Summary: attack api is a cli tool to find security vulnerabilities in an API.
Home-page: https://github.com/appknox/attackapi
Author: Appknox
Author-email: engineering@appknox.com
License: BSD
Platform: any
Classifier: Development Status :: 4 - Beta
Classifier: Environment :: Console
Classifier: Intended Audience :: Developers
Classifier: License :: OSI Approved :: BSD License
Classifier: Operating System :: POSIX
Classifier: Operating System :: MacOS
Classifier: Operating System :: Unix
Classifier: Programming Language :: Python
Classifier: Programming Language :: Python :: 3
Classifier: Topic :: Software Development :: Libraries :: Python Modules
